ipo_premium_client/__init__.py
ipo_premium_client/client.py
ipo_premium_client/exceptions.py
ipo_premium_client/mapper.py
ipo_premium_client/models.py
ipo_premium_client/utils.py
ipo_premium_client-1.0.13.dist-info/METADATA
ipo_premium_client-1.0.13.dist-info/WHEEL
ipo_premium_client-1.0.13.dist-info/top_level.txt
ipo_premium_client-1.0.13.dist-info/RECORD
